boyd_ml_utils/__init__.py
boyd_ml_utils/__version__.py
boyd_ml_utils/model_selection/__init__.py
boyd_ml_utils/model_selection/_search.py
boyd_ml_utils-0.4.1.dist-info/METADATA
boyd_ml_utils-0.4.1.dist-info/WHEEL
boyd_ml_utils-0.4.1.dist-info/RECORD
