Metadata-Version: 2.4
Name: boyd-ml-utils
Version: 0.4.1
Summary: machine learning utilities by boy-dad
Project-URL: Homepage, https://github.com/boy-dad/boyd-ml-utils
Requires-Python: >=3.10.12
Requires-Dist: lightgbm>=4.6.0
Requires-Dist: optuna<4.0.0,>=3.1.1
Requires-Dist: scikit-learn>=1.6.1
Requires-Dist: xgboost>=2.1.4
